README.rst
setup.py
djorm_ext_hstore.egg-info/PKG-INFO
djorm_ext_hstore.egg-info/SOURCES.txt
djorm_ext_hstore.egg-info/dependency_links.txt
djorm_ext_hstore.egg-info/not-zip-safe
djorm_ext_hstore.egg-info/requires.txt
djorm_ext_hstore.egg-info/top_level.txt
djorm_hstore/__init__.py
djorm_hstore/expressions.py
djorm_hstore/fields.py
djorm_hstore/forms.py
djorm_hstore/functions.py
djorm_hstore/models.py
djorm_hstore/query_utils.py
djorm_hstore/util.py
djorm_hstore/widgets.py
djorm_hstore/tests/__init__.py
djorm_hstore/tests/forms.py
djorm_hstore/tests/models.py